<?xml version = '1.0' encoding = 'UTF-8'?>
<relationalModel class="oracle.dbtools.crest.model.design.relational.RelationalDesign" name="Relational_1" id="BCF01D30-25D4-3D27-254E-FFDD73012248" mainViewID="D6060DE3-AAB6-BBB4-588F-A1D4B319A908">
<createdBy>Erick Marín</createdBy>
<createdTime>2015-06-26 17:09:15 UTC</createdTime>
<ownerDesignName>modelo_relacional_hr</ownerDesignName>
<shouldBeOpen>false</shouldBeOpen>
<selectedRDBMSSite>32076570-2523-435C-2E92-BF29817DFF70</selectedRDBMSSite>
<importConnectionStamps>
<importConnectionStamp class="oracle.dbtools.crest.imports.DBConnectionStamp">
<connName>Conexion HR</connName>
<connUrl>jdbc:oracle:thin:@localhost:1521:xe</connUrl>
<connUser>hr</connUser>
<connType>1</connType>
</importConnectionStamp>
</importConnectionStamps>
</relationalModel>